setup.py
ananother2/__init__.py
ananother2/module.py
ananother2.egg-info/PKG-INFO
ananother2.egg-info/SOURCES.txt
ananother2.egg-info/dependency_links.txt
ananother2.egg-info/requires.txt
ananother2.egg-info/top_level.txt